megdiffusion/__init__.py
megdiffusion/loss.py
megdiffusion/optimizer.py
megdiffusion/data/__init__.py
megdiffusion/data/cifar10.py
megdiffusion/data/image_folder.py
megdiffusion/diffusion/__init__.py
megdiffusion/diffusion/gaussion.py
megdiffusion/diffusion/schedule.py
megdiffusion/model/__init__.py
megdiffusion/model/ddpm.py
megdiffusion/model/ema.py
megdiffusion/model/iddpm.py
megdiffusion/model/pretrain/__init__.py
megdiffusion/model/pretrain/ddpm.py
megdiffusion/model/pretrain/iddpm.py
megdiffusion/pipeline/__init__.py
megdiffusion/utils/__init__.py
megdiffusion/utils/transform.py
megdiffusion/utils/vision.py
tests/__init__.py
tests/units/__init__.py
tests/units/test_ema.py
tests/units/test_make_grid.py
tests/units/test_models.py
megdiffusion-0.0.2.dist-info/LICENSE
megdiffusion-0.0.2.dist-info/METADATA
megdiffusion-0.0.2.dist-info/WHEEL
megdiffusion-0.0.2.dist-info/top_level.txt
megdiffusion-0.0.2.dist-info/RECORD
