Metadata-Version: 2.1
Name: megdiffusion
Version: 0.0.2
Summary: MegEngine implementation of Diffusion Models
Author: Chai
Classifier: Programming Language :: Python :: 3
Classifier: License :: OSI Approved :: MIT License
Classifier: Operating System :: OS Independent
License-File: LICENSE
